patractinterface/__init__.py
patractinterface/base.py
patractinterface/contract.py
patractinterface/observer.py
patractinterface/contracts/__init__.py
patractinterface/contracts/erc20.py
patractinterface/unittest/__init__.py
patractinterface/unittest/env.py
test/__init__.py
test/test_base.py
test/test_contract_api.py
test/test_erc20.py
test/test_erc20_observer.py
test/test_unittest_env.py
test/test_workround.py
patract_interface-0.3.4.dist-info/METADATA
patract_interface-0.3.4.dist-info/WHEEL
patract_interface-0.3.4.dist-info/top_level.txt
patract_interface-0.3.4.dist-info/RECORD
