Metadata-Version: 2.1
Name: patract-interface
Version: 0.3.4
Summary: Substrate Contract SDK for Python As a part of Himalia
Home-page: https://github.com/patractlabs/py-patract
Author: patractlabs
Author-email: polkadev@protonmail.com
License: UNKNOWN
Keywords: contract interface polkascan polkadot substrate blockchain rpc kusama
Platform: UNKNOWN
Classifier: Development Status :: 3 - Alpha
Classifier: Intended Audience :: Developers
Classifier: Topic :: Software Development
Classifier: License :: OSI Approved :: MIT License
Classifier: Programming Language :: Python :: 3
Classifier: Programming Language :: Python :: 3.5
Classifier: Programming Language :: Python :: 3.6
Classifier: Programming Language :: Python :: 3.7
Classifier: Programming Language :: Python :: 3.8
Classifier: Programming Language :: Python :: 3 :: Only
Requires-Python: >=3.6, <4
Requires-Dist: websocket-client (>=0.57.0)
Requires-Dist: base58 (>=2.0.1)
Requires-Dist: certifi (>=2020.11.8)
Requires-Dist: idna (>=2.8)
Requires-Dist: requests (>=2.25.0)
Requires-Dist: xxhash (>=1.3.0)
Requires-Dist: scalecodec (>=0.10.41)
Requires-Dist: py-sr25519-bindings (>=0.1.2)
Requires-Dist: py-ed25519-bindings (>=0.1.2)
Requires-Dist: py-bip39-bindings (>=0.1.6)
Requires-Dist: executor (>=23.2)
Requires-Dist: scalecodec (>=0.11.0)
Requires-Dist: substrate-interface (>=0.13.2)
Provides-Extra: test
Requires-Dist: coverage ; extra == 'test'
Requires-Dist: pytest ; extra == 'test'
